{
	"articles": [
		{
			"display":true,
			"title":"Display and Visibility",
			"articleImageAlt":"Display & Visibility",
			"category":["CSS","HTML"],
			"author":"Swapnika",
			"date":"",
			"description":"Block and inline elements. To observe the difference when applying visibility and display property",
			"articleImageUrl":"resources/images/articleThumbnails/DisplayAndVisibility.png",
			"articleUrl":"./ariticles/DisplayAndVisibility.html"
		},{
			"display":true,
			"title":"Position Property",
			"articleImageAlt":"Position Property",
			"category":["CSS"],
			"author":"Swapnika",
			"date":"",
			"description":"Position property: 'position' property is used to specify the positioning of an element. There are four basic values to define the positioning method to be adopted by the element they are: 'static', 'relative', 'absolute' and 'fixed'",
			"articleImageUrl":"resources/images/articleThumbnails/PositionProperty.png",
			"articleUrl":"./ariticles/PositionArticle.html"
		},{
			"display":true,
			"title":"Block & Inline Elements",
			"articleImageAlt":"Block & Inline Elements",
			"category":["HTML"],
			"author":"Swapnika",
			"date":"",
			"description":"By default HTML elements fall in to two categories for the way they render/lay in a document: i.e, Block & Inline.",
			"articleImageUrl":"resources/images/articleThumbnails/BlockInlineElements.png",
			"articleUrl":"./ariticles/BlockInlineElements.html"
		},{
			"display":true,
			"title":"Float And Clear",
			"articleImageAlt":"Float And Clear Elements",
			"category":["CSS","HTML"],
			"author":"Swapnika",
			"date":"",
			"description":"To arrange block elements linearly that is horizontally one next to other the block  element, float property is made to set to 'left' or 'right'.",
			"articleImageUrl":"resources/images/articleThumbnails/FloatAndClear.png",
			"articleUrl":"./ariticles/FloatAndClear.html"
		},{
			"display":true,
			"title":"Vertically align Child Elements",
			"articleImageAlt":"Vertically Aligning Child Elements",
			"category":["CSS"],
			"author":"Swapnika",
			"date":"",
			"description":"By default HTML elements fall in to two categories for the way they render/lay in a document: i.e, Block & Inline.",
			"articleImageUrl":"resources/images/articleThumbnails/VerticallyAlignChild.png",
			"articleUrl":"./ariticles/VerticallyAlignChild.html"
		},{
			"display":true,
			"title":"CSS Box Model",
			"articleImageAlt":"CSS Box Model",
			"category":["CSS"],
			"author":"Swapnika",
			"date":"",
			"description":"Box that wraps every element.",
			"articleImageUrl":"resources/images/articleThumbnails/boxModel.png",
			"articleUrl":"./ariticles/boxModel.html"
		},{
			"display":true,
			"title":"CSS Selectors",
			"articleImageAlt":"CSS Selectors",
			"category":["CSS"],
			"author":"Swapnika",
			"date":"",
			"description":"CSS Selectors enable us to cherry pick each and every element/group of elements to style them.",
			"articleImageUrl":"resources/images/articleThumbnails/selectors.png",
			"articleUrl":"./ariticles/selectorsArticle.html"
		},{
			"display":true,
			"title":"Function Currying",
			"articleImageAlt":"Function Currying",
			"category":["JS"],
			"author":"Swapnika",
			"date":"",
			"description":"Function Currying is constructing a function that allows partial application of arguments.",
			"articleImageUrl":"resources/images/articleThumbnails/functionCurrying.png",
			"articleUrl":"./ariticles/functionCurrying.html"
		}
    ]
}